elhub_sdk/__init__.py
elhub_sdk/client.py
elhub_sdk/constants.py
elhub_sdk/consumption.py
elhub_sdk/enrollment.py
elhub_sdk/enums.py
elhub_sdk/settings.py
elhub_sdk/third_party.py
elhub_sdk/wsdl/prod/2.3/bim/Acknowledgement.xsd
elhub_sdk/wsdl/prod/2.3/bim/PollForData.xsd
elhub_sdk/wsdl/prod/2.3/bim/common/Elhub_AggregatedBusinessInformationEntities.xsd
elhub_sdk/wsdl/prod/2.3/bim/common/Elhub_BusinessDataType.xsd
elhub_sdk/wsdl/prod/2.3/bim/market/ConfirmEndOfSupply.xsd
elhub_sdk/wsdl/prod/2.3/bim/market/ConfirmStartOfSupply.xsd
elhub_sdk/wsdl/prod/2.3/bim/market/NotifyEndOfSupply.xsd
elhub_sdk/wsdl/prod/2.3/bim/market/NotifyStartOfSupply.xsd
elhub_sdk/wsdl/prod/2.3/bim/market/RejectEndOfSupply.xsd
elhub_sdk/wsdl/prod/2.3/bim/market/RejectStartOfSupply.xsd
elhub_sdk/wsdl/prod/2.3/bim/market/RequestEndOfSupply.xsd
elhub_sdk/wsdl/prod/2.3/bim/market/RequestStartOfSupply.xsd
elhub_sdk/wsdl/prod/2.3/bim/masterdata/NotifyCustomerInformation.xsd
elhub_sdk/wsdl/prod/2.3/bim/masterdata/NotifyMeteringPointCharacteristics.xsd
elhub_sdk/wsdl/prod/2.3/bim/masterdata/RequestUpdateCustomerInformation.xsd
elhub_sdk/wsdl/prod/2.3/bim/masterdata/RequestUpdateMasterDataMeteringPoint.xsd
elhub_sdk/wsdl/prod/2.3/bim/metering/CollectedData.xsd
elhub_sdk/wsdl/prod/2.3/bim/metering/NotifyValidatedDataForBillingEnergy.xsd
elhub_sdk/wsdl/prod/2.3/bim/metering/PriceVolumeCombinationForReconciliation.xsd
elhub_sdk/wsdl/prod/2.3/bim/metering/RequestCollectedData.xsd
elhub_sdk/wsdl/prod/2.3/bim/query/RequestDataFromElhub.xsd
elhub_sdk/wsdl/prod/2.3/bim/query/RequestToElhub.xsd
elhub_sdk/wsdl/prod/2.3/bim/query/RequestToGridAccessProvider.xsd
elhub_sdk/wsdl/prod/2.3/bim/query/RequestUpfrontMeteringPointCharacteristics.xsd
elhub_sdk/wsdl/prod/2.3/bim/query/ResponseFromElhub.xsd
elhub_sdk/wsdl/prod/2.3/bim/query/ResponseFromGridAccessProvider.xsd
elhub_sdk/wsdl/prod/2.3/bim/query/ResponseUpfrontMeteringPointCharacteristics.xsd
elhub_python_sdk-0.1.4.dist-info/LICENSE
elhub_python_sdk-0.1.4.dist-info/METADATA
elhub_python_sdk-0.1.4.dist-info/WHEEL
elhub_python_sdk-0.1.4.dist-info/RECORD
